murmurai_server/__init__.py
murmurai_server/__main__.py
murmurai_server/auth.py
murmurai_server/config.py
murmurai_server/database.py
murmurai_server/deps.py
murmurai_server/logging.py
murmurai_server/main.py
murmurai_server/model_manager.py
murmurai_server/models.py
murmurai_server/server.py
murmurai_server/transcriber.py
murmurai-1.0.3.dist-info/METADATA
murmurai-1.0.3.dist-info/WHEEL
murmurai-1.0.3.dist-info/entry_points.txt
murmurai-1.0.3.dist-info/licenses/LICENSE
murmurai-1.0.3.dist-info/RECORD
