Metadata-Version: 2.4
Name: murmurai
Version: 1.0.3
Summary: GPU-powered transcription API with speaker diarization
Project-URL: Homepage, https://github.com/namastexlabs/murmurai
Project-URL: Repository, https://github.com/namastexlabs/murmurai.git
Project-URL: Issues, https://github.com/namastexlabs/murmurai/issues
Author: Felipe Rosa, Namastex Labs
License: MIT
License-File: LICENSE
Keywords: api,diarization,murmurai,speech-to-text,transcription,whisper
Classifier: Development Status :: 4 - Beta
Classifier: Environment :: GPU :: NVIDIA CUDA
Classifier: Framework :: FastAPI
Classifier: License :: OSI Approved :: MIT License
Classifier: Operating System :: OS Independent
Classifier: Programming Language :: Python :: 3.12
Classifier: Topic :: Multimedia :: Sound/Audio :: Speech
Requires-Python: ==3.12.*
Requires-Dist: aiosqlite>=0.19
Requires-Dist: fastapi>=0.100
Requires-Dist: httpx>=0.25
Requires-Dist: murmurai-core>=1.0.1
Requires-Dist: pydantic-settings>=2.0
Requires-Dist: pydantic>=2.0
Requires-Dist: python-dotenv>=1.0
Requires-Dist: python-multipart>=0.0.6
Requires-Dist: torch>=2.9.0
Requires-Dist: torchaudio>=2.8.0
Requires-Dist: torchvision>=0.24.1
Requires-Dist: uvicorn>=0.20
